Metadata-Version: 2.4
Name: ci-test
Version: 0.0.6
Summary: A framework for static analysis testing of CI configurations.
Author: Evan Kohilas
Project-URL: Homepage, https://github.com/ekohilas/ci-test
Project-URL: Issues, https://github.com/ekohilas/ci-test/issues
Classifier: Programming Language :: Python :: 3
Classifier: Operating System :: OS Independent
Classifier: License :: OSI Approved :: Mozilla Public License 2.0 (MPL 2.0)
Requires-Python: >=3.9
License-File: LICENSE
Dynamic: license-file
